toon_tuna-0.1.1.dist-info/METADATA
toon_tuna-0.1.1.dist-info/WHEEL
toon_tuna-0.1.1.dist-info/entry_points.txt
toon_tuna-0.1.1.dist-info/licenses/LICENSE
toon_tuna/__init__.py
toon_tuna/_toon_tuna.cpython-311-darwin.so
toon_tuna/cli.py
toon_tuna-0.1.1.dist-info/RECORD
